skdict/__init__.py
scikit_dict-0.1.0.dist-info/LICENSE
scikit_dict-0.1.0.dist-info/METADATA
scikit_dict-0.1.0.dist-info/WHEEL
scikit_dict-0.1.0.dist-info/top_level.txt
scikit_dict-0.1.0.dist-info/RECORD
