Metadata-Version: 2.1
Name: scikit-dict
Version: 0.1.0
Summary: Define Scikit-Learn objects 
Home-page: UNKNOWN
Author: Matheus Couto
Author-email: matheusccouto@gmail.com
License: UNKNOWN
Platform: UNKNOWN
License-File: LICENSE
Requires-Dist: scikit-learn
